setup.cfg
setup.py
Flask_FeatureFlags.egg-info/PKG-INFO
Flask_FeatureFlags.egg-info/SOURCES.txt
Flask_FeatureFlags.egg-info/dependency_links.txt
Flask_FeatureFlags.egg-info/not-zip-safe
Flask_FeatureFlags.egg-info/requires.txt
Flask_FeatureFlags.egg-info/top_level.txt
flask_featureflags/__init__.py
flask_featureflags/contrib/__init__.py
flask_featureflags/contrib/inline/__init__.py
flask_featureflags/contrib/sqlalchemy/__init__.py