Metadata-Version: 1.1
Name: Flask-FeatureFlags
Version: 0.6
Summary: Enable or disable features in Flask apps based on configuration
Home-page: https://github.com/trustrachel/Flask-FeatureFlags
Author: Rachel Sanders
Author-email: rachel@trustrachel.com
License: Apache
Platform: any
Classifier: Development Status :: 3 - Alpha
Classifier: Environment :: Web Environment
Classifier: Intended Audience :: Developers
Classifier: License :: OSI Approved :: Apache Software License
Classifier: Operating System :: OS Independent
Classifier: Programming Language :: Python
Classifier: Topic :: Internet :: WWW/HTTP :: Dynamic Content
Classifier: Topic :: Software Development :: Libraries :: Python Modules
